wonk/__init__.py
wonk/aws.py
wonk/cli.py
wonk/config.py
wonk/constants.py
wonk/exceptions.py
wonk/models.py
wonk/optimizer.py
wonk/policy.py
wonk-0.8.0.dist-info/WHEEL
wonk-0.8.0.dist-info/entry_points.txt
wonk-0.8.0.dist-info/METADATA
wonk-0.8.0.dist-info/RECORD
