Metadata-Version: 2.4
Name: wonk
Version: 0.8.0
Summary: Wonk is a tool for combining a set of AWS policy files into smaller compiled policy sets.
Author: Kirk Strauser
Author-email: Kirk Strauser <kirk@strauser.com>
License-Expression: Apache-2.0
Classifier: Development Status :: 5 - Production/Stable
Classifier: Intended Audience :: System Administrators
Classifier: License :: OSI Approved :: Apache Software License
Classifier: Programming Language :: Python :: 3
Classifier: Programming Language :: Python :: 3.9
Classifier: Programming Language :: Python :: 3.10
Classifier: Programming Language :: Python :: 3.11
Classifier: Programming Language :: Python :: 3.12
Classifier: Programming Language :: Python :: 3.13
Classifier: Topic :: System :: Systems Administration
Requires-Dist: boto3>=1.17
Requires-Dist: ortools>=9.3
Requires-Dist: pydantic>=1.8
Requires-Dist: pyyaml>=5.0
Requires-Dist: toposort>=1.6
Requires-Dist: xdg>=5.0
Requires-Python: >=3.9
